LICENSE
MANIFEST.in
README.md
requirements.txt
setup.py
pyauto/__init__.py
pyauto.secret.egg-info/PKG-INFO
pyauto.secret.egg-info/SOURCES.txt
pyauto.secret.egg-info/dependency_links.txt
pyauto.secret.egg-info/requires.txt
pyauto.secret.egg-info/top_level.txt
pyauto/secret/__init__.py
pyauto/secret/commands.py
pyauto/secret/config.py
pyauto/secret/store.py
pyauto/secret/tool.py
pyauto/secret/utils.py