Metadata-Version: 1.0
Name: pyauto.secret
Version: 0.0.1
Summary: A flexible module for generating and tracking shared secrets
Home-page: https://github.com/adamjaso/pyauto/tree/master/secret
Author: Adam Jaso
Author-email: UNKNOWN
License: GNU General Public License V2
Platform: UNKNOWN
